getraodata/__init__.py
getraodata/exceptions.py
getraodata/getraodata.py
tests/__init__.py
tests/test_getraodata.py
getRAOdata-0.1.13.dist-info/LICENSE
getRAOdata-0.1.13.dist-info/METADATA
getRAOdata-0.1.13.dist-info/WHEEL
getRAOdata-0.1.13.dist-info/entry_points.txt
getRAOdata-0.1.13.dist-info/top_level.txt
getRAOdata-0.1.13.dist-info/RECORD
