Metadata-Version: 2.1
Name: getRAOdata
Version: 0.1.13
Summary: Radioastronomy Observatory of Institute of Solar-Terrestrial Physics data downloader
Home-page: https://git.iszf.irk.ru/RAO/getraodata
Author: Yuri Aksenov
Author-email: ura2112@iszf.irk.ru
License: UNKNOWN
Platform: UNKNOWN
Classifier: Programming Language :: Python :: 3
Classifier: License :: OSI Approved :: MIT License
Classifier: Operating System :: OS Independent
Requires-Dist: raodata (==0.1.10)
Requires-Dist: python-dateutil (==2.8.1)
